mkdocs_awesome_pages_plugin/__init__.py
mkdocs_awesome_pages_plugin/meta.py
mkdocs_awesome_pages_plugin/navigation.py
mkdocs_awesome_pages_plugin/options.py
mkdocs_awesome_pages_plugin/plugin.py
mkdocs_awesome_pages_plugin/utils.py
mkdocs_awesome_pages_plugin-2.10.0.dist-info/LICENSE.md
mkdocs_awesome_pages_plugin-2.10.0.dist-info/METADATA
mkdocs_awesome_pages_plugin-2.10.0.dist-info/WHEEL
mkdocs_awesome_pages_plugin-2.10.0.dist-info/entry_points.txt
mkdocs_awesome_pages_plugin-2.10.0.dist-info/RECORD
