Metadata-Version: 2.1
Name: mkdocs-awesome-pages-plugin
Version: 2.10.0
Summary: An MkDocs plugin that simplifies configuring page titles and their order
Home-page: https://github.com/lukasgeiter/mkdocs-awesome-pages-plugin/
License: MIT
Keywords: mkdocs,python,markdown,wiki
Author: Lukas Geiter
Author-email: info@lukasgeiter.com
Requires-Python: >=3.8.1
Classifier: Development Status :: 5 - Production/Stable
Classifier: Intended Audience :: Developers
Classifier: Intended Audience :: Information Technology
Classifier: License :: OSI Approved :: MIT License
Classifier: Programming Language :: Python :: 3
Classifier: Programming Language :: Python :: 3.9
Classifier: Programming Language :: Python :: 3.10
Classifier: Programming Language :: Python :: 3.11
Classifier: Programming Language :: Python :: 3.12
Requires-Dist: mkdocs (>=1)
Requires-Dist: natsort (>=8.1.0)
Requires-Dist: wcmatch (>=7)
Project-URL: Repository, https://github.com/lukasgeiter/mkdocs-awesome-pages-plugin/
